npmstat/__init__.py
npmstat/_version.py
npmstat/api.py
npmstat/cli.py
npmstat/py.typed
npmstat-0.1.2.dist-info/METADATA
npmstat-0.1.2.dist-info/WHEEL
npmstat-0.1.2.dist-info/entry_points.txt
npmstat-0.1.2.dist-info/licenses/LICENSE
npmstat-0.1.2.dist-info/RECORD
