Metadata-Version: 2.4
Name: npmstat
Version: 0.1.2
Summary: Get NPM Package Stats and Info from the command line or as a Python module.
Project-URL: Changelog, https://github.com/cssnr/npmstat/releases
Project-URL: Discord, https://discord.gg/wXy6m2X8wY
Project-URL: Documentation, https://cssnr.github.io/npmstat/
Project-URL: Download, https://github.com/cssnr/npmstat/releases/latest
Project-URL: Funding, https://ko-fi.com/cssnr
Project-URL: GitHub, https://github.com/cssnr/npmstat
Project-URL: Homepage, https://cssnr.com/
Project-URL: Issues, https://github.com/cssnr/npmstat/issues
Author: Shane
License: MIT License
License-File: LICENSE
Classifier: Natural Language :: English
Classifier: Operating System :: OS Independent
Classifier: Programming Language :: Python
Classifier: Programming Language :: Python :: 3
Classifier: Programming Language :: Python :: 3 :: Only
Classifier: Typing :: Typed
Requires-Python: >=3.10
Requires-Dist: requests-cache<2,>=1
Requires-Dist: requests<3,>=2
Requires-Dist: typer>=0.19.0
